great_expectations_geospatial_expectations/__init__.py
great_expectations_geospatial_expectations/expectations/__init__.py
great_expectations_geospatial_expectations/expectations/expect_column_average_lat_lon_pairwise_distance_to_be_less_than.py
great_expectations_geospatial_expectations/expectations/expect_column_average_to_be_within_range_of_given_point.py
great_expectations_geospatial_expectations/expectations/expect_column_minimum_bounding_radius_to_be_between.py
great_expectations_geospatial_expectations/expectations/expect_column_pair_values_lat_lng_matches_geohash.py
great_expectations_geospatial_expectations/expectations/expect_column_values_geometry_centroids_to_be_within_shape.py
great_expectations_geospatial_expectations/expectations/expect_column_values_geometry_distance_to_address_to_be_between.py
great_expectations_geospatial_expectations/expectations/expect_column_values_geometry_not_to_overlap.py
great_expectations_geospatial_expectations/expectations/expect_column_values_geometry_to_be_near_shape.py
great_expectations_geospatial_expectations/expectations/expect_column_values_geometry_to_be_of_type.py
great_expectations_geospatial_expectations/expectations/expect_column_values_geometry_to_be_within_place.py
great_expectations_geospatial_expectations/expectations/expect_column_values_geometry_to_be_within_shape.py
great_expectations_geospatial_expectations/expectations/expect_column_values_geometry_to_intersect_shape.py
great_expectations_geospatial_expectations/expectations/expect_column_values_geometry_to_overlap.py
great_expectations_geospatial_expectations/expectations/expect_column_values_lat_lon_to_be_land_or_ocean.py
great_expectations_geospatial_expectations/expectations/expect_column_values_point_within_geo_region.py
great_expectations_geospatial_expectations/expectations/expect_column_values_reverse_geocoded_lat_lon_to_contain.py
great_expectations_geospatial_expectations-0.1.0.dist-info/LICENSE
great_expectations_geospatial_expectations-0.1.0.dist-info/METADATA
great_expectations_geospatial_expectations-0.1.0.dist-info/WHEEL
great_expectations_geospatial_expectations-0.1.0.dist-info/top_level.txt
great_expectations_geospatial_expectations-0.1.0.dist-info/RECORD
