Metadata-Version: 2.1
Name: great-expectations-geospatial-expectations
Version: 0.1.0
Summary: A collection of Expectations to validate Geospatial data with Great Expectations.
Author: Great Expectations
Author-email: austin@greatexpectations.io
License-File: LICENSE
Requires-Dist: geopandas
Requires-Dist: geopy
Requires-Dist: global-land-mask
Requires-Dist: great-expectations
Requires-Dist: pygeos
Requires-Dist: python-geohash
Requires-Dist: rtree
Requires-Dist: scikit-learn
Requires-Dist: scipy
Requires-Dist: setuptools
Requires-Dist: Shapely
Requires-Dist: timezonefinder
Requires-Dist: uszipcode
